adk_testlab-0.0.1.dist-info/DESCRIPTION.rst
adk_testlab-0.0.1.dist-info/METADATA
adk_testlab-0.0.1.dist-info/RECORD
adk_testlab-0.0.1.dist-info/WHEEL
adk_testlab-0.0.1.dist-info/metadata.json
adk_testlab-0.0.1.dist-info/top_level.txt
helloworld/__init__.py
helloworld/hello.py
test/__init__.py
test/test1.py
