Metadata-Version: 2.0
Name: adk-testlab
Version: 0.0.1
Summary: A personal reference collection of test projects for my development efforts.
Home-page: https://github.com/knightman/adk-testlab
Author: Andrew Knight
Author-email: knight.andrew@gmail.com
License: MIT
Keywords: knight testing lab
Platform: UNKNOWN
Classifier: Development Status :: 3 - Alpha
Classifier: License :: OSI Approved :: MIT License
